horast/__init__.py
horast/_logging.py
horast/_version.py
horast/ast_comments.py
horast/ast_dosctrings.py
horast/ast_tools.py
horast/ast_validator.py
horast/nodes.py
horast/parser.py
horast/py.typed
horast/token_tools.py
horast/unparser.py
horast-0.4.0.dist-info/LICENSE
horast-0.4.0.dist-info/METADATA
horast-0.4.0.dist-info/NOTICE
horast-0.4.0.dist-info/WHEEL
horast-0.4.0.dist-info/top_level.txt
horast-0.4.0.dist-info/RECORD
